README.rst
setup.py
logan/__init__.py
logan/importer.py
logan/runner.py
logan/settings.py
logan.egg-info/PKG-INFO
logan.egg-info/SOURCES.txt
logan.egg-info/dependency_links.txt
logan.egg-info/not-zip-safe
logan.egg-info/top_level.txt
tests/logan/__init__.py
tests/logan/runner/__init__.py
tests/logan/runner/tests.py
tests/logan/settings/__init__.py
tests/logan/settings/tests.py