Metadata-Version: 1.1
Name: logan
Version: 0.5.8.2
Summary: Logan is a toolkit for building standalone Django applications.
Home-page: http://github.com/dcramer/logan
Author: David Cramer
Author-email: dcramer@gmail.com
License: Apache License 2.0
Platform: UNKNOWN
Classifier: Framework :: Django
Classifier: Intended Audience :: Developers
Classifier: Intended Audience :: System Administrators
Classifier: Operating System :: OS Independent
Classifier: Topic :: Software Development
